tx/readable_log.py
tx/parallex/__init__.py
tx/parallex/data.py
tx/parallex/dependentqueue.py
tx/parallex/io.py
tx/parallex/objectstore.py
tx/parallex/plasma.py
tx/parallex/process.py
tx/parallex/python.py
tx/parallex/schema.json
tx/parallex/spec.py
tx/parallex/task.py
tx/parallex/utils.py
tx_parallex-0.1.11.dist-info/LICENSE
tx_parallex-0.1.11.dist-info/METADATA
tx_parallex-0.1.11.dist-info/WHEEL
tx_parallex-0.1.11.dist-info/top_level.txt
tx_parallex-0.1.11.dist-info/RECORD
