Metadata-Version: 2.1
Name: tx-parallex
Version: 0.1.11
Summary: A job queue with data dependencies
Home-page: https://github.com/RENCI/tx-parallex
Author: Hao Xu
Author-email: xuhao@renci.org
License: MIT
Platform: UNKNOWN
Classifier: Programming Language :: Python :: 3
Classifier: License :: OSI Approved :: MIT License
Classifier: Operating System :: OS Independent
Requires-Python: >=3.8
Requires-Dist: more-itertools (==8.2.0)
Requires-Dist: jsonschema (==3.2.0)
Requires-Dist: pyyaml (==5.3.1)
Requires-Dist: tx-functional (>=0.1.2)
Requires-Dist: graph-theory (==2020.5.6.39102)
Requires-Dist: terminaltables (==3.1.0)
Requires-Dist: jsonpickle (==1.4.1)
Provides-Extra: arrow
Requires-Dist: pyarrow (==1.0.0) ; extra == 'arrow'
